{
	"class" : {
		 },
	"instance" : {
		"creationTime" : "je 3/1/2019 11:25",
		"creationTime:" : "je 3/1/2019 11:25",
		"exceptionContext" : "SL 7/15/2017 17:49",
		"exceptionLine" : "SL 7/15/2017 18:38",
		"exceptionMessage" : "SL 7/15/2017 18:57",
		"exceptionType" : "SL 7/15/2017 18:44",
		"exceptions" : "PG 8/4/2017 16:33",
		"exceptions:" : "PG 8/4/2017 16:33",
		"expirationTime" : "je 3/1/2019 11:47",
		"firstException" : "topa 10/14/2015 13:38",
		"initialize" : "je 3/1/2019 11:44",
		"isExpired" : "je 3/1/2019 11:48",
		"lineNumberOfException" : "SL 7/15/2017 20:10",
		"runCase:" : "rhi 10/12/2017 12:42",
		"sourceRangeOfException" : "ck 9/19/2018 10:40",
		"storeException:for:" : "PG 8/4/2017 16:34",
		"testContext" : "rhi 10/12/2017 12:29",
		"testSource" : "SL 7/15/2017 18:34" } }
